galaxy_release_util/__init__.py
galaxy_release_util/bootstrap_history.py
galaxy_release_util/github_client.py
galaxy_release_util/metadata.py
galaxy_release_util/point_release.py
galaxy_release_util/py.typed
galaxy_release_util/util.py
galaxy_release_util/cli/__init__.py
galaxy_release_util/cli/options.py
galaxy_release_util/cli/release_util.py
galaxy_release_util-0.3.2.dist-info/METADATA
galaxy_release_util-0.3.2.dist-info/WHEEL
galaxy_release_util-0.3.2.dist-info/entry_points.txt
galaxy_release_util-0.3.2.dist-info/top_level.txt
galaxy_release_util-0.3.2.dist-info/RECORD
