Metadata-Version: 2.4
Name: galaxy-release-util
Version: 0.3.2
Summary: Utlity for various tasks around creating Galaxy releases
Home-page: https://github.com/galaxyproject/galaxy-release-util
Author: Galaxy Project and Community
Author-email: galaxy-committers@lists.galaxyproject.org
License: AFL
Keywords: Galaxy
Classifier: Development Status :: 5 - Production/Stable
Classifier: Environment :: Console
Classifier: Intended Audience :: Developers
Classifier: License :: OSI Approved :: Academic Free License (AFL)
Classifier: Natural Language :: English
Classifier: Operating System :: POSIX
Classifier: Programming Language :: Python :: 3
Classifier: Programming Language :: Python :: 3.8
Classifier: Programming Language :: Python :: 3.9
Classifier: Programming Language :: Python :: 3.10
Classifier: Programming Language :: Python :: 3.11
Classifier: Programming Language :: Python :: 3.12
Classifier: Topic :: Software Development
Classifier: Topic :: Software Development :: Code Generators
Classifier: Topic :: Software Development :: Testing
Requires-Python: >=3.8
Requires-Dist: build
Requires-Dist: click
Requires-Dist: python-dateutil
Requires-Dist: docutils
Requires-Dist: packaging
Requires-Dist: PyGithub
Requires-Dist: requests
Requires-Dist: twine
